{"name":"Nila","tagline":"A Dialect of Coffeescript with a Rubyspired Syntax","body":"## Welcome to Nila\r\n\r\nNila is a dialect of Coffeescript that leans towards a more Ruby oriented syntax. Originally it was planned to be a Ruby to Javascript compiler through Coffeescript.\r\n\r\n## Documentation\r\n\r\nDocumentation of the language is taking shape at https://github.com/adhithyan15/nila/wiki/Documentation\r\n\r\n## Authors and License\r\n\r\nThe project is licensed under MIT License. Please review license.md for more details.The project is being written and maintained by Adhithya Rajasekaran (@adhithyan15) and Sri Madhavi Rajasekaran(@sri96).  \r\n","google":"","note":"Don't delete this file! It's used internally to help with page regeneration."}